{
    "key": "group_64ac261630a2b",
    "title": "Container Width",
    "fields": [
        {
            "key": "field_64abe3e652672",
            "label": "Container Width",
            "name": "container_width",
            "aria-label": "",
            "type": "select",
            "instructions": "",
            "required": 0,
            "conditional_logic": 0,
            "wrapper": {
                "width": "",
                "class": "",
                "id": ""
            },
            "choices": {
                "container-xs": "Small",
                "container-small": "Normal",
                "container-wide": "Wide",
                "container-widest": "Wider",
                "container-xl": "Extra Wide",
                "container-full": "Full Width"
            },
            "default_value": "container-small",
            "return_format": "value",
            "multiple": 0,
            "allow_null": 0,
            "ui": 0,
            "ajax": 0,
            "placeholder": ""
        }
    ],
    "location": [
        [
            {
                "param": "post_type",
                "operator": "!=",
                "value": "post"
            },
            {
                "param": "post_type",
                "operator": "!=",
                "value": "page"
            },
            {
                "param": "post_type",
                "operator": "!=",
                "value": "popup"
            }
        ]
    ],
    "menu_order": 0,
    "position": "normal",
    "style": "default",
    "label_placement": "top",
    "instruction_placement": "label",
    "hide_on_screen": "",
    "active": true,
    "description": "",
    "show_in_rest": 0,
    "modified": 1690297058
}